{
	"roles": [
		{
			"id": "ROLE_DAMAGE",
			"name": "Damage"
		},
		{
			"id": "ROLE_SUPPORT",
			"name": "Support"
		},
		{
			"id": "ROLE_HEALER",
			"name": "Healer"
		}
	],

	"elements": [
		{
			"id": "ELEMENT_ANEMO",
			"name": "Anemo"
		},
		{
			"id": "ELEMENT_PYRO",
			"name": "Pyro"
		},
		{
			"id": "ELEMENT_ELECTRO",
			"name": "Electro"
		},
		{
			"id": "ELEMENT_HYDRO",
			"name": "Hydro"
		},
		{
			"id": "ELEMENT_CRYO",
			"name": "Cryo"
		},
		{
			"id": "ELEMENT_GEO",
			"name": "Geo"
		},
		{
			"id": "ELEMENT_DENDRO",
			"name": "Dendro"
		}
	],

	"characters": [
		{
			"name": "Albedo",
			"id": "CHARACTER_ALBEDO",
			"stars": 5,
			"colour": "yellow",
			"element": "ELEMENT_GEO",
			"rating": {
				"ROLE_DAMAGE":  [3.5, 3.5, 3.5, 3.5, 3.5, 3.5, 3.5],
				"ROLE_SUPPORT": [4, 4, 4, 4, 4, 4, 4],
				"ROLE_HEALER":  [0, 0, 0, 0, 0, 0, 0]
			}
		},
		{
			"name": "Amber",
			"id": "CHARACTER_AMBER",
			"stars": 4,
			"colour": "purple",
			"element": "ELEMENT_PYRO",
			"rating": {
				"ROLE_DAMAGE":  [1, 1, 1, 1, 1, 1, 1],
				"ROLE_SUPPORT": [1, 1, 1, 1, 1, 1, 1],
				"ROLE_HEALER":  [0, 0, 0, 0, 0, 0, 0]
			}
		},
		{
			"name": "Ayaka",
			"id": "CHARACTER_AYAKA",
			"stars": 5,
			"colour": "yellow",
			"element": "ELEMENT_CRYO",
			"rating": {
				"ROLE_DAMAGE":  [5, 5.1, 5.2, 5.3, 5.4, 5.5, 5.6],
				"ROLE_SUPPORT": [5, 5.1, 5.2, 5.3, 5.4, 5.5, 5.5],
				"ROLE_HEALER":  [0, 0, 0, 0, 0, 0, 0]
			}
		},
		{
			"name": "Barbara",
			"id": "CHARACTER_BARBARA",
			"stars": 4,
			"colour": "purple",
			"element": "ELEMENT_HYDRO",
			"rating": {
				"ROLE_DAMAGE":  [1, 1, 1, 1, 1, 1, 1],
				"ROLE_SUPPORT": [3, 3, 3, 3, 3, 3, 3],
				"ROLE_HEALER":  [3.5, 3.5, 3.5, 3.5, 3.5, 3.5, 4]
			}
		},
		{
			"name": "Beidou",
			"id": "CHARACTER_BEIDOU",
			"stars": 4,
			"colour": "purple",
			"element": "ELEMENT_ELECTRO",
			"rating": {
				"ROLE_DAMAGE":  [2, 2, 2, 2, 3, 3, 3],
				"ROLE_SUPPORT": [2, 2, 2, 2, 2, 2, 2],
				"ROLE_HEALER":  [0, 0, 0, 0, 0, 0, 0]
			}
		},
		{
			"name": "Bennett",
			"id": "CHARACTER_BENNETT",
			"stars": 4,
			"colour": "purple",
			"element": "ELEMENT_PYRO",
			"rating": {
				"ROLE_DAMAGE":  [3, 3, 3, 3, 3, 3, 3],
				"ROLE_SUPPORT": [5, 5, 5, 5, 5, 5, 5],
				"ROLE_HEALER":  [4, 5, 5, 5, 5, 5, 5]
			}
		},
		{
			"name": "Chongyun",
			"id": "CHARACTER_CHONGYUN",
			"stars": 4,
			"colour": "purple",
			"element": "ELEMENT_CRYO",
			"rating": {
				"ROLE_DAMAGE":  [2, 2, 2, 2, 2, 2, 2],
				"ROLE_SUPPORT": [3, 3, 3, 3, 3, 3, 3],
				"ROLE_HEALER":  [0, 0, 0, 0, 0, 0, 0]
			}
		},
		{
			"name": "Diluc",
			"id": "CHARACTER_DILUC",
			"stars": 5,
			"colour": "yellow",
			"element": "ELEMENT_PYRO",
			"rating": {
				"ROLE_DAMAGE":  [5, 5, 5, 5, 5, 5, 5],
				"ROLE_SUPPORT": [2, 2, 2, 2, 2, 2, 2],
				"ROLE_HEALER":  [0, 0, 0, 0, 0, 0, 0]
			}
		},
		{
			"name": "Diona",
			"id": "CHARACTER_DIONA",
			"stars": 4,
			"colour": "purple",
			"element": "ELEMENT_CRYO",
			"rating": {
				"ROLE_DAMAGE":  [2, 2, 2, 2, 2, 2, 2],
				"ROLE_SUPPORT": [3, 3, 3, 3, 3, 3, 3],
				"ROLE_HEALER":  [3, 4, 4, 4, 4, 4, 4]
			}
		},
		{
			"name": "Eula",
			"id": "CHARACTER_EULA",
			"stars": 5,
			"colour": "yellow",
			"element": "ELEMENT_CRYO",
			"rating": {
				"ROLE_DAMAGE":  [5, 5.1, 5.2, 5.3, 5.4, 5.5, 5.6],
				"ROLE_SUPPORT": [3, 3, 3.2, 3.2, 3.3, 3.4, 3.5],
				"ROLE_HEALER":  [0, 0, 0, 0, 0, 0, 0]
			}
		},
		{
			"name": "Fischl",
			"id": "CHARACTER_FISCHL",
			"stars": 4,
			"colour": "purple",
			"element": "ELEMENT_ELECTRO",
			"rating": {
				"ROLE_DAMAGE":  [3, 3, 3, 3, 3, 3, 4],
				"ROLE_SUPPORT": [4, 4, 4, 4, 4, 4, 4],
				"ROLE_HEALER":  [0, 0, 0, 0, 0, 0, 0]
			}
		},
		{
			"name": "Ganyu",
			"id": "CHARACTER_GANYU",
			"stars": 5,
			"colour": "yellow",
			"element": "ELEMENT_CRYO",
			"rating": {
				"ROLE_DAMAGE":  [5, 5, 5, 5, 5, 5, 5],
				"ROLE_SUPPORT": [5, 5, 5, 5, 5, 5, 5],
				"ROLE_HEALER":  [0, 0, 0, 0, 0, 0, 0]
			}
		},
		{
			"name": "Hu Tao",
			"id": "CHARACTER_HU_TAO",
			"stars": 5,
			"colour": "yellow",
			"element": "ELEMENT_PYRO",
			"rating": {
				"ROLE_DAMAGE":  [4, 5, 5, 5, 5, 5, 5],
				"ROLE_SUPPORT": [3, 3, 3, 3, 3, 3, 3],
				"ROLE_HEALER":  [0, 0, 0, 0, 0, 0, 0]
			}
		},
		{
			"name": "Jean",
			"id": "CHARACTER_JEAN",
			"stars": 5,
			"colour": "yellow",
			"element": "ELEMENT_ANEMO",
			"rating": {
				"ROLE_DAMAGE":  [3, 3, 3, 3, 3, 3, 3],
				"ROLE_SUPPORT": [4, 4, 4, 4, 4, 4, 4],
				"ROLE_HEALER":  [4, 4, 4, 4, 4, 4, 4]
			}
		},
		{
			"name": "Kaeya",
			"id": "CHARACTER_KAEYA",
			"stars": 4,
			"colour": "purple",
			"element": "ELEMENT_CRYO",
			"rating": {
				"ROLE_DAMAGE":  [1, 1, 1, 1, 1, 1, 1],
				"ROLE_SUPPORT": [3, 3, 3, 3, 3, 3, 3],
				"ROLE_HEALER":  [0, 0, 0, 0, 0, 0, 0]
			}
		},
		{
			"name": "Kazuha",
			"id": "CHARACTER_KAZUHA",
			"stars": 5,
			"colour": "yellow",
			"element": "ELEMENT_ANEMO",
			"rating": {
				"ROLE_DAMAGE":  [3.9, 4, 4.1, 4.2, 4.2, 4.3, 4.4],
				"ROLE_SUPPORT": [4, 4.1, 4.2, 4.2, 4.3, 4.3, 4.3],
				"ROLE_HEALER":  [0, 0, 0, 0, 0, 0, 0]
			}
		},
		{
			"name": "Keqing",
			"id": "CHARACTER_KEQING",
			"stars": 5,
			"colour": "yellow",
			"element": "ELEMENT_ELECTRO",
			"rating": {
				"ROLE_DAMAGE":  [4, 4, 4, 4, 4, 4, 4],
				"ROLE_SUPPORT": [3, 3, 3, 3, 3, 3, 3],
				"ROLE_HEALER":  [0, 0, 0, 0, 0, 0, 0]
			}
		},
		{
			"name": "Klee",
			"id": "CHARACTER_KLEE",
			"stars": 5,
			"colour": "yellow",
			"element": "ELEMENT_PYRO",
			"rating": {
				"ROLE_DAMAGE":  [5, 5, 5, 5, 5, 5, 5],
				"ROLE_SUPPORT": [3, 3, 3, 3, 3, 3, 3],
				"ROLE_HEALER":  [0, 0, 0, 0, 0, 0, 0]
			}
		},
		{
			"name": "Kokomi",
			"id": "CHARACTER_SANGONOMIYA_KOKOMI",
			"stars": 5,
			"colour": "yellow",
			"element": "ELEMENT_HYDRO",
			"rating": {
				"ROLE_DAMAGE":  [1, 1, 1, 1, 1, 1, 1],
				"ROLE_SUPPORT": [2, 2, 2, 2, 2, 2, 2],
				"ROLE_HEALER":  [2, 2, 2, 2, 2, 2, 2]
			}
		},
		{
			"name": "Lisa",
			"id": "CHARACTER_LISA",
			"stars": 4,
			"colour": "purple",
			"element": "ELEMENT_ELECTRO",
			"rating": {
				"ROLE_DAMAGE":  [1, 1, 1, 1, 1, 1, 1],
				"ROLE_SUPPORT": [2, 2, 2, 2, 2, 2, 2],
				"ROLE_HEALER":  [0, 0, 0, 0, 0, 0, 0]
			}
		},
		{
			"name": "Mona",
			"id": "CHARACTER_MONA",
			"stars": 5,
			"colour": "yellow",
			"element": "ELEMENT_HYDRO",
			"rating": {
				"ROLE_DAMAGE":  [3, 3, 3, 3, 3, 3, 3],
				"ROLE_SUPPORT": [5, 5, 5, 5, 5, 5, 5],
				"ROLE_HEALER":  [0, 0, 0, 0, 0, 0, 0]
			}
		},
		{
			"name": "Ningguang",
			"id": "CHARACTER_NINGGUANG",
			"stars": 4,
			"colour": "purple",
			"element": "ELEMENT_GEO",
			"rating": {
				"ROLE_DAMAGE":  [3, 4, 4, 4, 4, 4, 4],
				"ROLE_SUPPORT": [3, 3, 3, 3, 3, 3, 3],
				"ROLE_HEALER":  [0, 0, 0, 0, 0, 0, 0]
			}
		},
		{
			"name": "Noelle",
			"id": "CHARACTER_NOELLE",
			"stars": 4,
			"colour": "purple",
			"element": "ELEMENT_GEO",
			"rating": {
				"ROLE_DAMAGE":  [2, 2, 2, 2, 2, 2, 2],
				"ROLE_SUPPORT": [1, 2, 2, 2, 2, 2, 2],
				"ROLE_HEALER":  [1, 1, 1, 1, 1, 1, 1]
			}
		},
		{
			"name": "Qiqi",
			"id": "CHARACTER_QIQI",
			"stars": 5,
			"colour": "yellow",
			"element": "ELEMENT_CRYO",
			"rating": {
				"ROLE_DAMAGE":  [2, 2, 2, 2, 2, 2, 2],
				"ROLE_SUPPORT": [3, 3, 3, 3, 3, 3, 3],
				"ROLE_HEALER":  [4, 4, 4, 4, 4, 4, 4]
			}
		},
		{
			"name": "Shogun",
			"id": "CHARACTER_RAIDEN_SHOGUN",
			"stars": 5,
			"colour": "yellow",
			"element": "ELEMENT_ELECTRO",
			"rating": {
				"ROLE_DAMAGE":  [4, 4, 4, 4, 4, 4, 4],
				"ROLE_SUPPORT": [4, 4, 4, 4, 4, 4, 4],
				"ROLE_HEALER":  [0, 0, 0, 0, 0, 0, 0]
			}
		},
		{
			"name": "Razor",
			"id": "CHARACTER_RAZOR",
			"stars": 4,
			"colour": "purple",
			"element": "ELEMENT_ELECTRO",
			"rating": {
				"ROLE_DAMAGE":  [3, 3, 3, 3, 4, 4, 4],
				"ROLE_SUPPORT": [1, 1, 1, 1, 1, 1, 1],
				"ROLE_HEALER":  [0, 0, 0, 0, 0, 0, 0]
			}
		},
		{
			"name": "Rosaria",
			"id": "CHARACTER_ROSARIA",
			"stars": 4,
			"colour": "purple",
			"element": "ELEMENT_CRYO",
			"rating": {
				"ROLE_DAMAGE":  [3, 3.2, 4, 4.1, 4.2, 4.3, 4.4],
				"ROLE_SUPPORT": [3, 3.2, 4, 4.1, 4.3, 4.4, 4.4],
				"ROLE_HEALER":  [0, 0, 0, 0, 0, 0, 0]
			}
		},
		{
			"name": "Sara",
			"id": "CHARACTER_KUJOU_SARA",
			"stars": 4,
			"colour": "purple",
			"element": "ELEMENT_ELECTRO",
			"rating": {
				"ROLE_DAMAGE":  [1, 1, 1, 1, 1, 1, 1],
				"ROLE_SUPPORT": [2, 2, 2, 2, 2, 2, 2],
				"ROLE_HEALER":  [0, 0, 0, 0, 0, 0, 0]
			}
		},
		{
			"name": "Sayu",
			"id": "CHARACTER_SAYU",
			"stars": 4,
			"colour": "purple",
			"element": "ELEMENT_ANEMO",
			"rating": {
				"ROLE_DAMAGE":  [3, 3.1, 3.2, 3.3, 3.4, 3.5, 3.6],
				"ROLE_SUPPORT": [3.5, 3.6, 3.7, 3.8, 3.9, 4],
				"ROLE_HEALER":  [3.5, 3.6, 3.7, 3.8, 3.9, 4]
			}
		},
		{
			"name": "Sucrose",
			"id": "CHARACTER_SUCROSE",
			"stars": 4,
			"colour": "purple",
			"element": "ELEMENT_ANEMO",
			"rating": {
				"ROLE_DAMAGE":  [2, 2, 2, 2, 2, 2, 2],
				"ROLE_SUPPORT": [3, 4, 4, 4, 4, 4, 4],
				"ROLE_HEALER":  [0, 0, 0, 0, 0, 0, 0]
			}
		},
		{
			"name": "Tartaglia",
			"id": "CHARACTER_TARTAGLIA",
			"stars": 5,
			"colour": "yellow",
			"element": "ELEMENT_HYDRO",
			"rating": {
				"ROLE_DAMAGE":  [4, 4, 4, 4, 4, 4, 5],
				"ROLE_SUPPORT": [1, 1, 1, 1, 1, 1, 1],
				"ROLE_HEALER":  [0, 0, 0, 0, 0, 0, 0]
			}
		},
		{
			"name": "Traveller",
			"id": "CHARACTER_TRAVELLER_ANEMO",
			"stars": 5,
			"colour": "yellow",
			"element": "ELEMENT_ANEMO",
			"rating": {
				"ROLE_DAMAGE":  [0.9, 1, 1.1, 1.2, 1.3, 1.4, 1.5],
				"ROLE_SUPPORT": [1, 1.1, 1.2, 1.3, 1.4, 1.5, 1.6],
				"ROLE_HEALER":  [0, 0, 0, 0, 0, 0, 0]
			}
		},
		{
			"name": "Traveller",
			"id": "CHARACTER_TRAVELLER_GEO",
			"stars": 5,
			"colour": "yellow",
			"element": "ELEMENT_GEO",
			"rating": {
				"ROLE_DAMAGE":  [0.9, 1, 1.1, 1.2, 1.3, 1.4, 1.5],
				"ROLE_SUPPORT": [1, 1.1, 1.2, 1.3, 1.4, 1.5, 1.6],
				"ROLE_HEALER":  [0, 0, 0, 0, 0, 0, 0]
			}
		},
		{
			"name": "Traveller",
			"id": "CHARACTER_TRAVELLER_ELECTRO",
			"stars": 5,
			"colour": "yellow",
			"element": "ELEMENT_ELECTRO",
			"rating": {
				"ROLE_DAMAGE":  [2.0, 2.1, 2.2, 2.3, 2.4, 2.5, 2.6],
				"ROLE_SUPPORT": [3.0, 3.1, 3.2, 3.3, 3.4, 3.5, 3.6],
				"ROLE_HEALER":  [0, 0, 0, 0, 0, 0, 0]
			}
		},
		{
			"name": "Venti",
			"id": "CHARACTER_VENTI",
			"stars": 5,
			"colour": "yellow",
			"element": "ELEMENT_ANEMO",
			"rating": {
				"ROLE_DAMAGE":  [3, 3, 3, 3, 3, 3, 3],
				"ROLE_SUPPORT": [5, 5, 5, 5, 5, 5, 5],
				"ROLE_HEALER":  [0, 0, 0, 0, 0, 0, 0]
			}
		},
		{
			"name": "Xiangling",
			"id": "CHARACTER_XIANGLING",
			"stars": 4,
			"colour": "purple",
			"element": "ELEMENT_PYRO",
			"rating": {
				"ROLE_DAMAGE":  [3, 3, 3, 3, 3, 3, 3],
				"ROLE_SUPPORT": [3, 4, 4, 4, 4, 4, 4],
				"ROLE_HEALER":  [0, 0, 0, 0, 0, 0, 0]
			}
		},
		{
			"name": "Xiao",
			"id": "CHARACTER_XIAO",
			"stars": 5,
			"colour": "yellow",
			"element": "ELEMENT_ANEMO",
			"rating": {
				"ROLE_DAMAGE": [5, 5, 5, 5, 5, 5, 5],
				"ROLE_SUPPORT": [1, 1, 1, 1, 1, 1, 1],
				"ROLE_HEALER": [0, 0, 0, 0, 0, 0, 0]
			}
		},
		{
			"name": "Xingqiu",
			"id": "CHARACTER_XINGQIU",
			"stars": 4,
			"colour": "purple",
			"element": "ELEMENT_HYDRO",
			"rating": {
				"ROLE_DAMAGE":  [2, 2, 2, 2, 2, 2, 2],
				"ROLE_SUPPORT": [4, 4, 4, 4, 4, 4, 5],
				"ROLE_HEALER":  [0, 0, 0, 0, 0, 0, 0]
			}
		},
		{
			"name": "Xinyan",
			"id": "CHARACTER_XINYAN",
			"stars": 4,
			"colour": "purple",
			"element": "ELEMENT_PYRO",
			"rating": {
				"ROLE_DAMAGE":  [2, 2, 2, 3, 3, 3, 3],
				"ROLE_SUPPORT": [2, 2, 2, 2, 2, 2, 2],
				"ROLE_HEALER":  [0, 0, 0, 0, 0, 0, 0]
			}
		},
		{
			"name": "Yanfei",
			"id": "CHARACTER_YANFEI",
			"stars": 4,
			"colour": "purple",
			"element": "ELEMENT_PYRO",
			"rating": {
				"ROLE_DAMAGE":  [2, 3, 3.1, 3.2, 3.3, 3.4, 3.5],
				"ROLE_SUPPORT": [3, 3.1, 3.2, 3.3, 3.4, 3.5, 3.6],
				"ROLE_HEALER":  [0, 0, 0, 0, 0, 0, 0]
			}
		},
		{
			"name": "Yoimiya",
			"id": "CHARACTER_YOIMIYA",
			"stars": 5,
			"colour": "yellow",
			"element": "ELEMENT_PYRO",
			"rating": {
				"ROLE_DAMAGE":  [4, 4.1, 4.2, 4.3, 4.4, 4.5, 4.5],
				"ROLE_SUPPORT": [3.9, 4.0, 4.1, 4.2, 4.3, 4.4],
				"ROLE_HEALER":  [0, 0, 0, 0, 0, 0, 0]
			}
		},
		{
			"name": "Zhongli",
			"id": "CHARACTER_ZHONGLI",
			"stars": 5,
			"colour": "yellow",
			"element": "ELEMENT_GEO",
			"rating": {
				"ROLE_DAMAGE":  [3, 3, 3, 3, 3, 3, 3],
				"ROLE_SUPPORT": [5, 5, 5, 5, 5, 5, 5],
				"ROLE_HEALER":  [0, 0, 0, 0, 0, 0, 0]
			}
		}
	]
}
